onwebchange/__init__.py
onwebchange/__main__.py
onwebchange/core.py
onwebchange/webui.py
onwebchange/templates/index.html
onwebchange-0.3.4.dist-info/LICENSE
onwebchange-0.3.4.dist-info/METADATA
onwebchange-0.3.4.dist-info/WHEEL
onwebchange-0.3.4.dist-info/top_level.txt
onwebchange-0.3.4.dist-info/RECORD
