Metadata-Version: 2.1
Name: onwebchange
Version: 0.3.4
Summary: watchdog toolkit for check web change.
Home-page: https://github.com/ClericPy/onwebchange
Author: ClericPy
Author-email: clericpy@gmail.com
License: MIT License
Keywords: watchdog web change.
Platform: any
Classifier: Programming Language :: Python
Classifier: Programming Language :: Python :: 3
Classifier: Programming Language :: Python :: 3.6
Classifier: Programming Language :: Python :: 3.7
Requires-Dist: torequests
Requires-Dist: click
Requires-Dist: bottle
Requires-Dist: objectpath
Requires-Dist: beautifulsoup4
